{
  "terms": [
    {
      "x": [
        8
      ],
      "q_terms": [
        {
          "q": -7,
          "c": 1
        },
        {
          "q": -3,
          "c": 2
        },
        {
          "q": -2,
          "c": 1
        },
        {
          "q": -1,
          "c": -2
        },
        {
          "q": 0,
          "c": 1
        },
        {
          "q": 2,
          "c": 1
        },
        {
          "q": 3,
          "c": 3
        },
        {
          "q": 5,
          "c": -2
        },
        {
          "q": 6,
          "c": -1
        },
        {
          "q": 7,
          "c": 2
        },
        {
          "q": 11,
          "c": -1
        }
      ]
    },
    {
      "x": [
        3
      ],
      "q_terms": [
        {
          "q": -1,
          "c": -1
        }
      ]
    },
    {
      "x": [
        6
      ],
      "q_terms": [
        {
          "q": -4,
          "c": -1
        },
        {
          "q": -2,
          "c": 1
        },
        {
          "q": -1,
          "c": -2
        },
        {
          "q": 0,
          "c": 1
        },
        {
          "q": 3,
          "c": -1
        },
        {
          "q": 4,
          "c": -2
        }
      ]
    },
    {
      "x": [
        10
      ],
      "q_terms": [
        {
          "q": -11,
          "c": -1
        },
        {
          "q": -6,
          "c": -2
        },
        {
          "q": -3,
          "c": 1
        },
        {
          "q": -1,
          "c": -2
        },
        {
          "q": 1,
          "c": -5
        },
        {
          "q": 2,
          "c": -5
        },
        {
          "q": 4,
          "c": 2
        },
        {
          "q": 5,
          "c": 1
        },
        {
          "q": 6,
          "c": -3
        },
        {
          "q": 7,
          "c": -2
        },
        {
          "q": 9,
          "c": 2
        },
        {
          "q": 10,
          "c": 1
        },
        {
          "q": 11,
          "c": 1
        },
        {
          "q": 13,
          "c": -5
        },
        {
          "q": 14,
          "c": -3
        },
        {
          "q": 15,
          "c": -2
        },
        {
          "q": 16,
          "c": 1
        }
      ]
    },
    {
      "x": [
        13
      ],
      "q_terms": [
        {
          "q": -56,
          "c": -2
        },
        {
          "q": -46,
          "c": -6
        },
        {
          "q": -45,
          "c": -2
        },
        {
          "q": -44,
          "c": -2
        },
        {
          "q": -43,
          "c": -2
        },
        {
          "q": -42,
          "c": -2
        },
        {
          "q": -41,
          "c": -2
        },
        {
          "q": -40,
          "c": -2
        },
        {
          "q": -39,
          "c": -2
        },
        {
          "q": -38,
          "c": -6
        },
        {
          "q": -37,
          "c": -10
        },
        {
          "q": -36,
          "c": -14
        },
        {
          "q": -35,
          "c": -8
        },
        {
          "q": -34,
          "c": -10
        },
        {
          "q": -33,
          "c": -10
        },
        {
          "q": -32,
          "c": -14
        },
        {
          "q": -31,
          "c": -14
        },
        {
          "q": -30,
          "c": -28
        },
        {
          "q": -29,
          "c": -32
        },
        {
          "q": -28,
          "c": -44
        },
        {
          "q": -27,
          "c": -36
        },
        {
          "q": -26,
          "c": -52
        },
        {
          "q": -25,
          "c": -54
        },
        {
          "q": -24,
          "c": -72
        },
        {
          "q": -23,
          "c": -86
        },
        {
          "q": -22,
          "c": -126
        },
        {
          "q": -21,
          "c": -136
        },
        {
          "q": -20,
          "c": -164
        },
        {
          "q": -19,
          "c": -180
        },
        {
          "q": -18,
          "c": -228
        },
        {
          "q": -17,
          "c": -256
        },
        {
          "q": -16,
          "c": -329
        },
        {
          "q": -15,
          "c": -351
        },
        {
          "q": -14,
          "c": -421
        },
        {
          "q": -13,
          "c": -451
        },
        {
          "q": -12,
          "c": -528
        },
        {
          "q": -11,
          "c": -555
        },
        {
          "q": -10,
          "c": -648
        },
        {
          "q": -9,
          "c": -669
        },
        {
          "q": -8,
          "c": -756
        },
        {
          "q": -7,
          "c": -773
        },
        {
          "q": -6,
          "c": -881
        },
        {
          "q": -5,
          "c": -880
        },
        {
          "q": -4,
          "c": -980
        },
        {
          "q": -3,
          "c": -948
        },
        {
          "q": -2,
          "c": -1023
        },
        {
          "q": -1,
          "c": -996
        },
        {
          "q": 0,
          "c": -1020
        },
        {
          "q": 1,
          "c": -949
        },
        {
          "q": 2,
          "c": -985
        },
        {
          "q": 3,
          "c": -884
        },
        {
          "q": 4,
          "c": -877
        },
        {
          "q": 5,
          "c": -766
        },
        {
          "q": 6,
          "c": -752
        },
        {
          "q": 7,
          "c": -666
        },
        {
          "q": 8,
          "c": -651
        },
        {
          "q": 9,
          "c": -562
        },
        {
          "q": 10,
          "c": -541
        },
        {
          "q": 11,
          "c": -466
        },
        {
          "q": 12,
          "c": -430
        },
        {
          "q": 13,
          "c": -347
        },
        {
          "q": 14,
          "c": -317
        },
        {
          "q": 15,
          "c": -252
        },
        {
          "q": 16,
          "c": -236
        },
        {
          "q": 17,
          "c": -192
        },
        {
          "q": 18,
          "c": -167
        },
        {
          "q": 19,
          "c": -135
        },
        {
          "q": 20,
          "c": -122
        },
        {
          "q": 21,
          "c": -86
        },
        {
          "q": 22,
          "c": -69
        },
        {
          "q": 23,
          "c": -53
        },
        {
          "q": 24,
          "c": -52
        },
        {
          "q": 25,
          "c": -39
        },
        {
          "q": 26,
          "c": -50
        },
        {
          "q": 27,
          "c": -38
        },
        {
          "q": 28,
          "c": -31
        },
        {
          "q": 29,
          "c": -16
        },
        {
          "q": 30,
          "c": -13
        },
        {
          "q": 31,
          "c": -10
        },
        {
          "q": 32,
          "c": -10
        },
        {
          "q": 33,
          "c": -8
        },
        {
          "q": 34,
          "c": -14
        },
        {
          "q": 35,
          "c": -10
        },
        {
          "q": 36,
          "c": -6
        },
        {
          "q": 37,
          "c": -2
        },
        {
          "q": 38,
          "c": -2
        },
        {
          "q": 39,
          "c": -2
        },
        {
          "q": 40,
          "c": -2
        },
        {
          "q": 41,
          "c": -2
        },
        {
          "q": 42,
          "c": -2
        },
        {
          "q": 43,
          "c": -2
        },
        {
          "q": 44,
          "c": -6
        },
        {
          "q": 54,
          "c": -2
        }
      ]
    },
    {
      "x": [
        2
      ],
      "q_terms": [
        {
          "q": -1,
          "c": -1
        }
      ]
    },
    {
      "x": [
        7
      ],
      "q_terms": [
        {
          "q": -4,
          "c": -1
        },
        {
          "q": -3,
          "c": 1
        },
        {
          "q": -2,
          "c": 1
        },
        {
          "q": -1,
          "c": -2
        },
        {
          "q": 0,
          "c": 1
        },
        {
          "q": 2,
          "c": 1
        },
        {
          "q": 3,
          "c": 1
        },
        {
          "q": 4,
          "c": -2
        },
        {
          "q": 5,
          "c": -2
        },
        {
          "q": 6,
          "c": 1
        }
      ]
    },
    {
      "x": [
        4
      ],
      "q_terms": [
        {
          "q": -2,
          "c": 1
        },
        {
          "q": -1,
          "c": -1
        },
        {
          "q": 0,
          "c": 1
        }
      ]
    },
    {
      "x": [
        5
      ],
      "q_terms": [
        {
          "q": -2,
          "c": 1
        },
        {
          "q": -1,
          "c": -1
        },
        {
          "q": 0,
          "c": 1
        },
        {
          "q": 3,
          "c": -1
        }
      ]
    },
    {
      "x": [
        9
      ],
      "q_terms": [
        {
          "q": -7,
          "c": 1
        },
        {
          "q": -6,
          "c": -1
        },
        {
          "q": -3,
          "c": 2
        },
        {
          "q": -1,
          "c": -2
        },
        {
          "q": 1,
          "c": -2
        },
        {
          "q": 2,
          "c": -2
        },
        {
          "q": 3,
          "c": 3
        },
        {
          "q": 4,
          "c": 2
        },
        {
          "q": 5,
          "c": -1
        },
        {
          "q": 6,
          "c": -3
        },
        {
          "q": 8,
          "c": 2
        },
        {
          "q": 11,
          "c": -1
        },
        {
          "q": 12,
          "c": -2
        },
        {
          "q": 13,
          "c": -2
        }
      ]
    },
    {
      "x": [
        11
      ],
      "q_terms": [
        {
          "q": -11,
          "c": -1
        },
        {
          "q": -10,
          "c": 1
        },
        {
          "q": -9,
          "c": 1
        },
        {
          "q": -6,
          "c": -2
        },
        {
          "q": -5,
          "c": 1
        },
        {
          "q": -3,
          "c": 2
        },
        {
          "q": -2,
          "c": 2
        },
        {
          "q": -1,
          "c": 1
        },
        {
          "q": 0,
          "c": 3
        },
        {
          "q": 1,
          "c": -5
        },
        {
          "q": 2,
          "c": -8
        },
        {
          "q": 3,
          "c": -1
        },
        {
          "q": 4,
          "c": 2
        },
        {
          "q": 5,
          "c": 4
        },
        {
          "q": 6,
          "c": -1
        },
        {
          "q": 7,
          "c": -2
        },
        {
          "q": 8,
          "c": -2
        },
        {
          "q": 10,
          "c": 3
        },
        {
          "q": 11,
          "c": 3
        },
        {
          "q": 12,
          "c": 6
        },
        {
          "q": 13,
          "c": 1
        },
        {
          "q": 14,
          "c": -5
        },
        {
          "q": 15,
          "c": -6
        },
        {
          "q": 16,
          "c": -1
        },
        {
          "q": 18,
          "c": 2
        },
        {
          "q": 23,
          "c": -1
        }
      ]
    },
    {
      "x": [
        12
      ],
      "q_terms": [
        {
          "q": -16,
          "c": 1
        },
        {
          "q": -10,
          "c": 3
        },
        {
          "q": -9,
          "c": 1
        },
        {
          "q": -8,
          "c": -1
        },
        {
          "q": -6,
          "c": -1
        },
        {
          "q": -5,
          "c": 1
        },
        {
          "q": -3,
          "c": 2
        },
        {
          "q": -2,
          "c": 5
        },
        {
          "q": -1,
          "c": 5
        },
        {
          "q": 0,
          "c": 7
        },
        {
          "q": 1,
          "c": -3
        },
        {
          "q": 2,
          "c": -8
        },
        {
          "q": 3,
          "c": -3
        },
        {
          "q": 4,
          "c": 3
        },
        {
          "q": 5,
          "c": 5
        },
        {
          "q": 6,
          "c": 2
        },
        {
          "q": 8,
          "c": -3
        },
        {
          "q": 9,
          "c": -4
        },
        {
          "q": 10,
          "c": -4
        },
        {
          "q": 12,
          "c": 5
        },
        {
          "q": 13,
          "c": 10
        },
        {
          "q": 14,
          "c": 5
        },
        {
          "q": 15,
          "c": -8
        },
        {
          "q": 16,
          "c": -6
        },
        {
          "q": 17,
          "c": -4
        },
        {
          "q": 18,
          "c": 3
        },
        {
          "q": 19,
          "c": 1
        },
        {
          "q": 20,
          "c": 2
        },
        {
          "q": 23,
          "c": -1
        },
        {
          "q": 24,
          "c": -2
        },
        {
          "q": 25,
          "c": -2
        },
        {
          "q": 26,
          "c": -2
        }
      ]
    }
  ],
  "metadata": {
    "num_x_variables": 1,
    "max_x_degrees": [
      13
    ],
    "storage_type": "sparse",
    "braid": [
      -1,
      2,
      2,
      2,
      -1,
      -2,
      -2,
      -2,
      -2,
      -2
    ],
    "inversion": {
      "0": [
        -1,
        -1,
        1,
        -1,
        1,
        1,
        -1,
        1,
        -1,
        -1,
        -1,
        -1,
        -1,
        1,
        -1,
        1,
        1,
        -1,
        1,
        -1
      ]
    },
    "components": 1
  }
}